{"_id":"Chickenandpapayacasserole","preptime":"10","servings":"4","keywords":["cuisine@british contemporary","diet@corn-free","occasion@entertaining","main ingredient@poultry","meal type@main","cook method.hob, oven, grill@hob / oven","diet@egg-free","diet@cow dairy-free","occasion@prepare-ahead entertaining","diet@wheat-free","diet@peanut-free","diet@dairy-free","special collections@very easy","diet@citrus-free","diet@shellfish-free","diet@demi-veg","diet@gluten-free"],"subtitle":"A light summery casserole that's bursting with flavour.","totaltime":"80","cooktime":"70","ingredients":[{"ingredient":"dry white wine","measure":"150 ml"},{"ingredient":"caster sugar","measure":"1 tsp"},{"ingredient":"papaya","measure":"1"},{"ingredient":"seasoning","measure":""},{"ingredient":"onion","measure":"1"},{"ingredient":"chicken quarters","measure":"4"},{"ingredient":"red pepper","measure":"1"},{"ingredient":"green pepper","measure":"1"},{"ingredient":"canned chopped tomatoes","measure":"400 g"},{"ingredient":"olive oil","measure":"60 ml"},{"ingredient":"garlic","measure":"8 cloves-1 bulb"},{"ingredient":"black olives","measure":"6"}],"method":[{"step":"1","text":"Preheat oven to 180&deg;C."},{"step":"2","text":"Heat oil in a large frying pan. Add garlic and onion and fry for 2-3 min or until softened. Add chicken to pan and fry all over for 8-10 min or until golden brown."},{"step":"3","text":"Transfer garlic, onion and chicken to an ovenproof dish and scatter over the red and green pepper. Add tomatoes, wine and sugar to the dish with papaya, seasoning and olives and stir until well mixed."},{"step":"4","text":"Cover dish and cook in oven for 1 hour or until chicken is tender. Serve immediately."}],"title":"Chicken and papaya casserole"}