{"_id":"Creamymangofool","preptime":"15","servings":"6","keywords":["diet@vegetarian","diet@corn-free","occasion@entertaining","meal type@desserts","diet@egg-free","occasion@prepare-ahead entertaining","diet@peanut-free","diet@wheat-free","special collections@cheffy recommended","special collections@very easy","diet@citrus-free","occasion@buffet party","diet@shellfish-free","cook method@no cooking","diet@demi-veg","diet@gluten-free"],"subtitle":"A creamy, dreamy dessert.","totaltime":"75","cooktime":"0","ingredients":[{"ingredient":"mangos","measure":"2"},{"ingredient":"white wine","measure":"60 ml"},{"ingredient":"sweet sherry","measure":"60 ml"},{"ingredient":"vanilla essence","measure":"[sup]1[/sup]/[sub]4[/sub] tsp"},{"ingredient":"greek yogurt","measure":"150 ml"},{"ingredient":"custard","measure":"150 ml"},{"ingredient":"double cream","measure":"300 ml"},{"ingredient":null,"measure":""},{"ingredient":"double cream","measure":"150 ml"},{"ingredient":"mango","measure":"[sup]1[/sup]/[sub]4[/sub]"},{"ingredient":"fresh mint","measure":"6 sprigs"}],"method":[{"step":"1","text":"Puree the mango flesh and wine or sherry in a food processor or liquidiser. Pour into a mixing bowl. "},{"step":"2","text":"Fold the vanilla essence into the puree. Fold in the yogurt or custard and double cream. "},{"step":"3","text":"Spoon into individual dishes. Pipe a swirl of cream in the centre. Top with a mango slice and sprig of mint. Chill before serving."}],"title":"Creamy mango fool"}