{"_id":"Tomatohamandcurdcheeseflan","preptime":"10","servings":"4","keywords":["diet@peanut-free","diet@corn-free","diet@citrus-free","diet@yeast-free","diet@shellfish-free","occasion@picnic","convenience@serve with salad for complete meal","meal type@main","cook method.hob, oven, grill@hob / oven","meal type@main.quiches, flans","meal type@lunch / snacks"],"subtitle":"Serve this flan warm with salad or pack in your lunchbox to eat cold.","totaltime":"43","cooktime":"33","ingredients":[{"ingredient":"eggs","measure":"3"},{"ingredient":"milk","measure":"50 ml"},{"ingredient":"wafer thin ham","measure":"25 g"},{"ingredient":"tomato","measure":"1"},{"ingredient":"butter","measure":"7 g"},{"ingredient":"margarine","measure":"7 g"},{"ingredient":"wholemeal shortcrust pastry","measure":"500 g"},{"ingredient":"leek","measure":"1"},{"ingredient":"curd cheese","measure":"100 g"},{"ingredient":"fresh parsley","measure":"3 tsp"},{"ingredient":"seasoning","measure":""}],"method":[{"step":"1","text":"Preheat oven to 200&deg;C."},{"step":"2","text":"Roll out the pastry on a lightly floured surface and use to line two 13 cm round loose-based fluted flan tins. Chill for 10-15 min. Prick the bases. Place in the oven and bake blind for about 10 min until just cooked though."},{"step":"3","text":"Meanwhile, melt the butter or margarine in a pan and gently saute the leek for 3-5 min until softened. Cool slightly. "},{"step":"4","text":"Beat the curd cheese to soften. Slowly beat in the eggs and milk. Stir in the parsley and seasoning."},{"step":"5","text":"Divide the leeks, ham and tomato between the two cases. Pour in the egg mixture. "},{"step":"6","text":"Place in the oven for 20-25 min until just set and golden brown. Serve hot or cold."}],"title":"Tomato, ham and curd cheese flan"}