{"_id":"Tunafishcakes","preptime":"10","servings":"4","keywords":["cuisine@british contemporary","cook method.hob, oven, grill@hob","diet@peanut-free","diet@corn-free","special collections@very easy","diet@shellfish-free","main ingredient@fish","diet@demi-veg","meal type@main","meal type@lunch / snacks","special collections@weekday meal","special collections@store cupboard"],"subtitle":"Tuna makes a great store cupboard standby.","totaltime":"15","cooktime":"5","ingredients":[{"ingredient":"canned tuna in tomato sauce","measure":"225 g"},{"ingredient":"mashed potato","measure":"225 g"},{"ingredient":"onions","measure":"3 tsp"},{"ingredient":"lemon juice","measure":"1 tsp"},{"ingredient":"seasoning","measure":""},{"ingredient":"egg","measure":"1"},{"ingredient":"breadcrumbs","measure":"75 g"},{"ingredient":"oil for deep frying","measure":""}],"method":[{"step":"1","text":"Mix together tuna and sauce, potatoes, onion, lemon juice and season to taste. With floured hands, shape into 8 (2 per person) round flat cakes. Dip in beaten egg, then coat with breadcrumbs."},{"step":"2","text":"Fry fish cakes for 5-6 min or until golden brown. Drain on crumpled up kitchen paper. Serve piping hot."}],"title":"Tuna fish cakes"}